madonna/__init__.py
madonna/py.typed
madonna/version.py
madonna-0.2.0.dist-info/LICENSE
madonna-0.2.0.dist-info/WHEEL
madonna-0.2.0.dist-info/METADATA
madonna-0.2.0.dist-info/RECORD
